fastrelease/__init__.py
fastrelease/_nbdev.py
fastrelease/conda.py
fastrelease/core.py
fastrelease-0.1.17.dist-info/LICENSE
fastrelease-0.1.17.dist-info/METADATA
fastrelease-0.1.17.dist-info/WHEEL
fastrelease-0.1.17.dist-info/entry_points.txt
fastrelease-0.1.17.dist-info/top_level.txt
fastrelease-0.1.17.dist-info/RECORD
