Metadata-Version: 2.1
Name: fastrelease
Version: 0.1.17
Summary: Simplified releases using GitHub Issues
Home-page: https://github.com/fastai/fastrelease/tree/master/
Author: Jeremy Howard
Author-email: info@fast.ai
License: Apache Software License 2.0
Keywords: nbdev release github
Platform: UNKNOWN
Classifier: Development Status :: 4 - Beta
Classifier: Intended Audience :: Developers
Classifier: License :: OSI Approved :: Apache Software License
Classifier: Natural Language :: English
Classifier: Programming Language :: Python :: 3.6
Classifier: Programming Language :: Python :: 3.7
Classifier: Programming Language :: Python :: 3.8
Requires-Python: >=3.6
License-File: LICENSE
Requires-Dist: pip
Requires-Dist: packaging
Requires-Dist: ghapi
Requires-Dist: pyyaml
Requires-Dist: fastcore (>=1.3.13)
Provides-Extra: dev
